stringanalysis.py
stringanalysis/__init__.py
stringanalysis/string_analysis.py
ramon_stringanalysis-0.0.6.dist-info/LICENSE.txt
ramon_stringanalysis-0.0.6.dist-info/METADATA
ramon_stringanalysis-0.0.6.dist-info/WHEEL
ramon_stringanalysis-0.0.6.dist-info/top_level.txt
ramon_stringanalysis-0.0.6.dist-info/RECORD
